metax/__init__.py
metax/data/example_data/Example_Meta.tsv
metax/data/example_data/Example_OTF.tsv
metax/data/example_data/Example_Taxa.tsv
metax/data/example_data/Example_annotation.tsv
metax/data/example_data/Example_final_peptide.tsv
metax/database_builder/__init__.py
metax/database_builder/database_builder_mag.py
metax/database_builder/database_builder_own.py
metax/database_builder/download_mgyg_faa.py
metax/database_updater/__init__.py
metax/database_updater/database_updater.py
metax/gui/__init__.py
metax/gui/main_gui.py
metax/gui/metax_gui/__init__.py
metax/gui/metax_gui/checkable_combo_box.py
metax/gui/metax_gui/cmap_combo_box.py
metax/gui/metax_gui/command_window.py
metax/gui/metax_gui/console_window.py
metax/gui/metax_gui/drag_line_edit.py
metax/gui/metax_gui/extended_combo_box.py
metax/gui/metax_gui/generic_thread.py
metax/gui/metax_gui/input_window.py
metax/gui/metax_gui/matplotlib_figure_canvas.py
metax/gui/metax_gui/settings_widget.py
metax/gui/metax_gui/show_plt.py
metax/gui/metax_gui/show_plt_dialog.py
metax/gui/metax_gui/ui_func_threshold_help.py
metax/gui/metax_gui/ui_lca_help.py
metax/gui/metax_gui/ui_main_window.py
metax/gui/metax_gui/ui_setting_window.py
metax/gui/metax_gui/ui_table_view.py
metax/gui/metax_gui/user_agreement_dialog.py
metax/gui/metax_gui/web_dialog.py
metax/gui/metax_gui/resources/FUNC_prop.png
metax/gui/metax_gui/resources/LCA_prop.png
metax/gui/metax_gui/resources/NorthOmics_logo.png
metax/gui/metax_gui/resources/icon.qrc
metax/gui/metax_gui/resources/icon_rc.py
metax/gui/metax_gui/resources/logo.png
metax/peptide_annotator/__init__.py
metax/peptide_annotator/convert_id_to_name.py
metax/peptide_annotator/get_genome_rank.py
metax/peptide_annotator/metalab2otf.py
metax/peptide_annotator/pep_table_to_otf.py
metax/peptide_annotator/peptable_annotator.py
metax/peptide_annotator/proteins_to_taxafunc.py
metax/taxafunc_analyzer/analyzer.py
metax/taxafunc_analyzer/analyzer_utils/__init__.py
metaxtools-1.126.3.dist-info/licenses/LICENSE
metaxtools-1.126.3.dist-info/METADATA
metaxtools-1.126.3.dist-info/WHEEL
metaxtools-1.126.3.dist-info/entry_points.txt
metaxtools-1.126.3.dist-info/top_level.txt
metaxtools-1.126.3.dist-info/RECORD
