Metadata-Version: 2.4
Name: MetaXTools
Version: 1.126.3
Summary: MetaXTools is a novel tool for linking peptide sequences with taxonomic and functional information in Metaproteomics.
Author-email: Qing Wu <byeomax@outlook.com>
License-Expression: LicenseRef-My-Custom-License
Project-URL: Homepage, https://github.com/byemaxx/MetaX
Project-URL: Issues, https://github.com/byemaxx/MetaX/issues
Keywords: MetaX,MetaXTools,metaproteomics,peptide,OTF,Operational Taxa-Functions,visualization,analysis
Classifier: Programming Language :: Python :: 3
Classifier: Operating System :: OS Independent
Requires-Python: >=3.10
License-File: LICENSE
Requires-Dist: distinctipy>=1.2.2
Requires-Dist: matplotlib>=3.7.2
Requires-Dist: numpy>=1.25.1
Requires-Dist: pandas>=2.0.3
Requires-Dist: pydeseq2==0.4.12
Requires-Dist: pyecharts>=2.0.6
Requires-Dist: PyQt5>=5.15.9
Requires-Dist: PyQt5-Qt5>=5.15.2
Requires-Dist: PyQt5-sip>=12.12.1
Requires-Dist: PyQtWebEngine>=5.15.6
Requires-Dist: PyQtWebEngine-Qt5>=5.15.2
Requires-Dist: python-dateutil>=2.8.2
Requires-Dist: qt-material==2.14
Requires-Dist: QtAwesome>=1.2.3
Requires-Dist: scikit-learn>=1.3.0
Requires-Dist: scipy>=1.11.3
Requires-Dist: tqdm>=4.65.0
Requires-Dist: scikit-bio>=0.6.3
Requires-Dist: adjustText>=1.1.1
Requires-Dist: openpyxl
Requires-Dist: pyproject-toml>=0.0.10
Requires-Dist: statsmodels
Requires-Dist: seaborn>=0.13.2
Requires-Dist: numba>=0.60.0
Requires-Dist: UpSetPlot>=0.9.0
Dynamic: license-file
